spglm/__init__.py
spglm/base.py
spglm/family.py
spglm/glm.py
spglm/iwls.py
spglm/links.py
spglm/utils.py
spglm/varfuncs.py
spglm/tests/__init__.py
spglm/tests/test_glm.py
spglm-1.1.0.dist-info/LICENSE.txt
spglm-1.1.0.dist-info/METADATA
spglm-1.1.0.dist-info/WHEEL
spglm-1.1.0.dist-info/top_level.txt
spglm-1.1.0.dist-info/RECORD
