Metadata-Version: 2.1
Name: spglm
Version: 1.1.0
Summary: Sparse Generalized Linear Models
Maintainer-email: "Taylor M. Oshan" <tayoshan@gmail.com>
License: BSD 3-Clause
Project-URL: Home, https://pysal.org/spglm/
Project-URL: Repository, https://github.com/pysal/spglm
Keywords: spatial statistics
Classifier: Programming Language :: Python :: 3
Classifier: Programming Language :: Python :: 3.9
Classifier: Programming Language :: Python :: 3.10
Classifier: Programming Language :: Python :: 3.11
Classifier: License :: OSI Approved :: BSD License
Classifier: Operating System :: OS Independent
Classifier: Intended Audience :: Science/Research
Classifier: Topic :: Scientific/Engineering :: GIS
Requires-Python: >=3.9
License-File: LICENSE.txt
Requires-Dist: libpysal>=4.5
Requires-Dist: numpy>=1.23
Requires-Dist: scipy>=1.8
Requires-Dist: spreg>=1.2
Provides-Extra: dev
Requires-Dist: black; extra == "dev"
Requires-Dist: ruff; extra == "dev"
Requires-Dist: pre-commit; extra == "dev"
Provides-Extra: docs
Requires-Dist: nbsphinx; extra == "docs"
Requires-Dist: numpydoc; extra == "docs"
Requires-Dist: sphinx; extra == "docs"
Requires-Dist: sphinxcontrib-bibtex; extra == "docs"
Requires-Dist: sphinx_bootstrap_theme; extra == "docs"
Provides-Extra: tests
Requires-Dist: codecov; extra == "tests"
Requires-Dist: pytest; extra == "tests"
Requires-Dist: pytest-cov; extra == "tests"
Requires-Dist: pytest-xdist; extra == "tests"
Provides-Extra: all
Requires-Dist: spglm[dev,docs,tests]; extra == "all"
